<?xml version="1.0" encoding="UTF-8" standalone="no"?>
<configuration>

<driver id="modbus">
    <device id="str1_modbus">
      <description>String 1 Modbus RTU</description>
      <deviceAddress>/dev/ttyS1</deviceAddress>
      <settings>RTU:SERIAL_ENCODING_RTU:9600:DATABITS_8:PARITY_NONE:STOPBITS_1:ECHO_FALSE:FLOWCONTROL_NONE:FLOWCONTROL_NONE</settings>
      <samplingTimeout>3s</samplingTimeout>
      <connectRetryInterval>3s</connectRetryInterval>
      <disabled>false</disabled>
      <channel id="str1_cell1_1">
        <description>Cell (R) (str1_cell1)</description>
        <channelAddress>2:HOLDING_REGISTERS:1:INT16</channelAddress>
        <valueType>INTEGER</valueType>
        <samplingInterval>1s</samplingInterval>
        <samplingTimeOffset>0</samplingTimeOffset>
        <samplingGroup>str1_sg_slave_1</samplingGroup>
        <loggingInterval>1s</loggingInterval>
        <loggingSettings>sqllogger:</loggingSettings>
        <disabled>false</disabled>
      </channel>
      <channel id="str1_cell1_2">
        <description>Cell (V) (str1_cell1)</description>
        <channelAddress>2:HOLDING_REGISTERS:2:INT16</channelAddress>
        <valueType>INTEGER</valueType>
        <samplingInterval>1s</samplingInterval>
        <samplingTimeOffset>0</samplingTimeOffset>
        <samplingGroup>str1_sg_slave_1</samplingGroup>
        <loggingInterval>1s</loggingInterval>
        <loggingSettings>sqllogger:</loggingSettings>
        <disabled>false</disabled>
      </channel>
      <channel id="str1_cell1_3">
        <description>Cell (T) (str1_cell1)</description>
        <channelAddress>2:HOLDING_REGISTERS:3:INT16</channelAddress>
        <valueType>INTEGER</valueType>
        <samplingInterval>1s</samplingInterval>
        <samplingTimeOffset>0</samplingTimeOffset>
        <samplingGroup>str1_sg_slave_1</samplingGroup>
        <loggingInterval>1s</loggingInterval>
        <loggingSettings>sqllogger:</loggingSettings>
        <disabled>false</disabled>
      </channel>
      <channel id="str1_cell2_1">
        <description>Cell (R) (str1_cell2)</description>
        <channelAddress>3:HOLDING_REGISTERS:1:INT16</channelAddress>
        <valueType>INTEGER</valueType>
        <samplingInterval>1s</samplingInterval>
        <samplingTimeOffset>50ms</samplingTimeOffset>
        <samplingGroup>str1_sg_slave_2</samplingGroup>
        <loggingInterval>1s</loggingInterval>
        <loggingSettings>sqllogger:</loggingSettings>
        <disabled>false</disabled>
      </channel>
      <channel id="str1_cell2_2">
        <description>Cell (V) (str1_cell2)</description>
        <channelAddress>3:HOLDING_REGISTERS:2:INT16</channelAddress>
        <valueType>INTEGER</valueType>
        <samplingInterval>1s</samplingInterval>
        <samplingTimeOffset>50ms</samplingTimeOffset>
        <samplingGroup>str1_sg_slave_2</samplingGroup>
        <loggingInterval>1s</loggingInterval>
        <loggingSettings>sqllogger:</loggingSettings>
        <disabled>false</disabled>
      </channel>
      <channel id="str1_cell2_3">
        <description>Cell (T) (str1_cell2)</description>
        <channelAddress>3:HOLDING_REGISTERS:3:INT16</channelAddress>
        <valueType>INTEGER</valueType>
        <samplingInterval>1s</samplingInterval>
        <samplingTimeOffset>50ms</samplingTimeOffset>
        <samplingGroup>str1_sg_slave_2</samplingGroup>
        <loggingInterval>1s</loggingInterval>
        <loggingSettings>sqllogger:</loggingSettings>
        <disabled>false</disabled>
      </channel>
      <!--
      <channel id="str1_cell3_1">
        <description>Cell (R) (str1_cell3)</description>
        <channelAddress>3:HOLDING_REGISTERS:1:INT16</channelAddress>
        <valueType>INTEGER</valueType>
        <samplingInterval>1s</samplingInterval>
        <samplingTimeOffset>200ms</samplingTimeOffset>
        <samplingGroup>str1_sg_slave_3</samplingGroup>
        <loggingInterval>1s</loggingInterval>
        <loggingSettings>sqllogger:</loggingSettings>
        <disabled>false</disabled>
      </channel>
      <channel id="str1_cell3_2">
        <description>Cell (V) (str1_cell3)</description>
        <channelAddress>3:HOLDING_REGISTERS:2:INT16</channelAddress>
        <valueType>INTEGER</valueType>
        <samplingInterval>1s</samplingInterval>
        <samplingTimeOffset>200ms</samplingTimeOffset>
        <samplingGroup>str1_sg_slave_3</samplingGroup>
        <loggingInterval>1s</loggingInterval>
        <loggingSettings>sqllogger:</loggingSettings>
        <disabled>false</disabled>
      </channel>
      <channel id="str1_cell3_3">
        <description>Cell (T) (str1_cell3)</description>
        <channelAddress>3:HOLDING_REGISTERS:3:INT16</channelAddress>
        <valueType>INTEGER</valueType>
        <samplingInterval>1s</samplingInterval>
        <samplingTimeOffset>200ms</samplingTimeOffset>
        <samplingGroup>str1_sg_slave_3</samplingGroup>
        <loggingInterval>1s</loggingInterval>
        <loggingSettings>sqllogger:</loggingSettings>
        <disabled>false</disabled>
      </channel>
      <channel id="str1_cell4_1">
        <description>Cell (R) (str1_cell4)</description>
        <channelAddress>4:HOLDING_REGISTERS:1:INT16</channelAddress>
        <valueType>INTEGER</valueType>
        <samplingInterval>1s</samplingInterval>
        <samplingTimeOffset>300ms</samplingTimeOffset>
        <samplingGroup>str1_sg_slave_4</samplingGroup>
        <loggingInterval>1s</loggingInterval>
        <loggingSettings>sqllogger:</loggingSettings>
        <disabled>false</disabled>
      </channel>
      <channel id="str1_cell4_2">
        <description>Cell (V) (str1_cell4)</description>
        <channelAddress>4:HOLDING_REGISTERS:2:INT16</channelAddress>
        <valueType>INTEGER</valueType>
        <samplingInterval>1s</samplingInterval>
        <samplingTimeOffset>300ms</samplingTimeOffset>
        <samplingGroup>str1_sg_slave_4</samplingGroup>
        <loggingInterval>1s</loggingInterval>
        <loggingSettings>sqllogger:</loggingSettings>
        <disabled>false</disabled>
      </channel>
      <channel id="str1_cell4_3">
        <description>Cell (T) (str1_cell4)</description>
        <channelAddress>4:HOLDING_REGISTERS:3:INT16</channelAddress>
        <valueType>INTEGER</valueType>
        <samplingInterval>1s</samplingInterval>
        <samplingTimeOffset>300ms</samplingTimeOffset>
        <samplingGroup>str1_sg_slave_4</samplingGroup>
        <loggingInterval>1s</loggingInterval>
        <loggingSettings>sqllogger:</loggingSettings>
        <disabled>false</disabled>
      </channel> -->
    </device>
</driver>
</configuration>
